LICENSE
MANIFEST.in
README.rst
setup.py
django_tethys_apps.egg-info/PKG-INFO
django_tethys_apps.egg-info/SOURCES.txt
django_tethys_apps.egg-info/dependency_links.txt
django_tethys_apps.egg-info/entry_points.txt
django_tethys_apps.egg-info/requires.txt
django_tethys_apps.egg-info/top_level.txt
tethys_apps/.DS_Store
tethys_apps/__init__.py
tethys_apps/__init__.pyc
tethys_apps/admin.py
tethys_apps/admin.pyc
tethys_apps/app_harvester.py
tethys_apps/app_harvester.pyc
tethys_apps/app_installation.py
tethys_apps/app_installation.pyc
tethys_apps/context_processors.py
tethys_apps/context_processors.pyc
tethys_apps/helpers.py
tethys_apps/models.py
tethys_apps/models.pyc
tethys_apps/sdk.py
tethys_apps/terminal_colors.py
tethys_apps/urls.py
tethys_apps/urls.pyc
tethys_apps/utilities.py
tethys_apps/utilities.pyc
tethys_apps/views.py
tethys_apps/views.pyc
tethys_apps/base/__init__.py
tethys_apps/base/__init__.pyc
tethys_apps/base/app_base.py
tethys_apps/base/app_base.pyc
tethys_apps/base/controller.py
tethys_apps/base/controller.pyc
tethys_apps/base/persistent_store.py
tethys_apps/base/persistent_store.pyc
tethys_apps/base/url_map.py
tethys_apps/cli/__init__.py
tethys_apps/cli/__init__.pyc
tethys_apps/cli/docker_commands.py
tethys_apps/cli/gen_templates/__init__.py
tethys_apps/cli/gen_templates/apache
tethys_apps/cli/gen_templates/settings
tethys_apps/management/__init__.py
tethys_apps/management/commands/__init__.py
tethys_apps/management/commands/syncstores.py
tethys_apps/pastetemplates/__init__.py
tethys_apps/pastetemplates/__init__.pyc
tethys_apps/pastetemplates/tethysapp_template/.gitignore
tethys_apps/pastetemplates/tethysapp_template/__init__.py
tethys_apps/pastetemplates/tethysapp_template/setup.py_tmpl
tethys_apps/pastetemplates/tethysapp_template/tethysapp/__init__.py
tethys_apps/pastetemplates/tethysapp_template/tethysapp/+project+/__init__.py
tethys_apps/pastetemplates/tethysapp_template/tethysapp/+project+/app.py_tmpl
tethys_apps/pastetemplates/tethysapp_template/tethysapp/+project+/controllers.py_tmpl
tethys_apps/pastetemplates/tethysapp_template/tethysapp/+project+/init_stores.py
tethys_apps/pastetemplates/tethysapp_template/tethysapp/+project+/model.py
